ModelChat/__init__.py
modelchat-0.0.1.dist-info/METADATA
modelchat-0.0.1.dist-info/WHEEL
modelchat-0.0.1.dist-info/licenses/LICENSE
modelchat-0.0.1.dist-info/RECORD
