Metadata-Version: 2.1
Name: ModelChat
Version: 0.0.1
Summary: Una libreria para usar modelos de Chat en huggingface
Author-email: Emiliano Cuellar <ec446162@gmail.com>
License-File: LICENSE
Classifier: License :: OSI Approved :: MIT License
Classifier: Operating System :: OS Independent
Classifier: Programming Language :: Python :: 3
Requires-Python: >=3.7
Requires-Dist: requests
